asyncrunner/.gitignore
asyncrunner/__init__.py
asyncrunner/async_tools.py
async_task_runner-1.0.3.dist-info/METADATA
async_task_runner-1.0.3.dist-info/WHEEL
async_task_runner-1.0.3.dist-info/RECORD
