Metadata-Version: 2.3
Name: async-task-runner
Version: 1.0.3
Summary: An asyncio-based asynchronous task runner, ready to use out of the box.
License: MIT
Author: huangyanming
Author-email: 13528685024@163.com
Requires-Python: >=3.9
Classifier: License :: OSI Approved :: MIT License
Classifier: Operating System :: OS Independent
Classifier: Programming Language :: Python :: 3
Classifier: Programming Language :: Python :: 3.9
Classifier: Programming Language :: Python :: 3.10
Classifier: Programming Language :: Python :: 3.11
Classifier: Programming Language :: Python :: 3.12
Classifier: Programming Language :: Python :: 3.13
Project-URL: Documentation, https://github.com/869413421/asyncrunner
Project-URL: Homepage, https://github.com/869413421/asyncrunner
Project-URL: Repository, https://github.com/869413421/asyncrunner
